{
	"credit": "Made with Blockbench",
	"textures": {
		"0": "eyecandycraftdecor:block/estintoretarga",
		"particle": "eyecandycraftdecor:block/estintoretarga"
	},
	"elements": [
		{
			"from": [6, 3, 1],
			"to": [10, 12, 5],
			"faces": {
				"north": {"uv": [6, 2, 8, 6.5], "texture": "#0"},
				"east": {"uv": [0, 2, 2, 6.5], "texture": "#0"},
				"south": {"uv": [2, 2, 4, 6.5], "texture": "#0"},
				"west": {"uv": [4, 2, 6, 6.5], "texture": "#0"},
				"up": {"uv": [2, 0, 4, 2], "texture": "#0"},
				"down": {"uv": [4, 0, 6, 2], "texture": "#0"}
			}
		},
		{
			"from": [6.5, 12, 1.5],
			"to": [9.5, 13, 4.5],
			"faces": {
				"north": {"uv": [2.625, 0.21875, 5.625, 1.21875], "texture": "#0"},
				"east": {"uv": [2.5625, 0.1875, 5.5625, 1.1875], "texture": "#0"},
				"south": {"uv": [2.5625, 0.15625, 5.5625, 1.15625], "texture": "#0"},
				"west": {"uv": [2.53125, 0.15625, 5.53125, 1.15625], "texture": "#0"},
				"up": {"uv": [2, 0, 4, 2], "texture": "#0"},
				"down": {"uv": [4, 0, 6, 2], "texture": "#0"}
			}
		},
		{
			"from": [6.5, 2, 1.5],
			"to": [9.5, 3, 4.5],
			"faces": {
				"north": {"uv": [2.625, 0.21875, 5.625, 1.21875], "texture": "#0"},
				"east": {"uv": [2.5625, 0.1875, 5.5625, 1.1875], "texture": "#0"},
				"south": {"uv": [2.5625, 0.15625, 5.5625, 1.15625], "texture": "#0"},
				"west": {"uv": [2.53125, 0.15625, 5.53125, 1.15625], "texture": "#0"},
				"up": {"uv": [2, 0, 4, 2], "texture": "#0"},
				"down": {"uv": [4, 0, 6, 2], "texture": "#0"}
			}
		},
		{
			"from": [7.5, 11, 0],
			"to": [8.5, 12, 1],
			"faces": {
				"north": {"uv": [6, 9.5, 7, 10.5], "texture": "#0"},
				"east": {"uv": [6, 9.5, 7, 10.5], "texture": "#0"},
				"south": {"uv": [6, 9.5, 7, 10.5], "texture": "#0"},
				"west": {"uv": [6, 9.5, 7, 10.5], "texture": "#0"},
				"up": {"uv": [6.4375, 9.625, 6.65625, 10.34375], "texture": "#0"},
				"down": {"uv": [6, 9.5, 7, 10.5], "texture": "#0"}
			}
		},
		{
			"from": [7.5, 13, 2.5],
			"to": [8.5, 14, 3.5],
			"faces": {
				"north": {"uv": [6.25, 9.90625, 6.34375, 10.28125], "texture": "#0"},
				"east": {"uv": [6.21875, 9.78125, 6.625, 10.1875], "texture": "#0"},
				"south": {"uv": [6, 9.5, 7, 10.5], "texture": "#0"},
				"west": {"uv": [6.3125, 9.6875, 6.71875, 9.875], "texture": "#0"},
				"up": {"uv": [0, 0, 1, 1], "texture": "#missing"},
				"down": {"uv": [0, 0, 1, 1], "texture": "#missing"}
			}
		},
		{
			"from": [6.5, 14, 2.5],
			"to": [10.5, 15, 3.5],
			"faces": {
				"north": {"uv": [6, 9.53125, 6.9375, 10.53125], "texture": "#0"},
				"east": {"uv": [6, 9.53125, 6.875, 10.4375], "texture": "#0"},
				"south": {"uv": [5.5, 8, 7.5, 8.5], "texture": "#0"},
				"west": {"uv": [6, 9.5, 7, 10.5], "texture": "#0"},
				"up": {"uv": [6, 9.5, 7, 10.5], "rotation": 90, "texture": "#0"},
				"down": {"uv": [6.4375, 9.875, 6.8125, 10.25], "rotation": 270, "texture": "#0"}
			}
		},
		{
			"from": [16, 4.25, 2.5],
			"to": [18.5, 5.25, 3.499],
			"rotation": {"angle": 45, "axis": "z", "origin": [0, 0, 0]},
			"faces": {
				"north": {"uv": [6.5, 9.8125, 6.71875, 10.15625], "texture": "#0"},
				"east": {"uv": [6, 9.5, 7, 10.5], "texture": "#0"},
				"south": {"uv": [6, 9.5, 6.875, 10.5], "texture": "#0"},
				"west": {"uv": [5.96875, 9.5, 6.96875, 10.5], "texture": "#0"},
				"up": {"uv": [6.09375, 9.6875, 6.75, 10.21875], "rotation": 90, "texture": "#0"},
				"down": {"uv": [6.03125, 9.53125, 6.65625, 10.03125], "rotation": 270, "texture": "#0"}
			}
		}
	]
}